conftest.py
sklearn_evaluation/__init__.py
sklearn_evaluation/compute.py
sklearn_evaluation/evaluator.py
sklearn_evaluation/exceptions.py
sklearn_evaluation/metrics.py
sklearn_evaluation/table.py
sklearn_evaluation/tracker.py
sklearn_evaluation/util.py
sklearn_evaluation/validate.py
sklearn_evaluation/assets/nb/template.html
sklearn_evaluation/assets/report/classifier.md
sklearn_evaluation/grid/__init__.py
sklearn_evaluation/grid/classifier_grid.py
sklearn_evaluation/grid/random_forest_classifier_grid.py
sklearn_evaluation/nb/NotebookCollection.py
sklearn_evaluation/nb/NotebookDatabase.py
sklearn_evaluation/nb/NotebookIntrospector.py
sklearn_evaluation/nb/__init__.py
sklearn_evaluation/nb/sets.py
sklearn_evaluation/plot/__init__.py
sklearn_evaluation/plot/_example.py
sklearn_evaluation/plot/_matrix.py
sklearn_evaluation/plot/calibration.py
sklearn_evaluation/plot/classification.py
sklearn_evaluation/plot/classification_report.py
sklearn_evaluation/plot/clustering.py
sklearn_evaluation/plot/confusion_matrix_interactive.py
sklearn_evaluation/plot/cumulative_gain_lift_curve.py
sklearn_evaluation/plot/feature_ranking.py
sklearn_evaluation/plot/grid_search.py
sklearn_evaluation/plot/ks_statistics.py
sklearn_evaluation/plot/learning_curve.py
sklearn_evaluation/plot/metrics.py
sklearn_evaluation/plot/pca.py
sklearn_evaluation/plot/plot.py
sklearn_evaluation/plot/precision_recall.py
sklearn_evaluation/plot/regression.py
sklearn_evaluation/plot/roc.py
sklearn_evaluation/plot/style.py
sklearn_evaluation/plot/target_analysis.py
sklearn_evaluation/plot/util.py
sklearn_evaluation/plot/validation_curve.py
sklearn_evaluation/plot/matplotlib/__init__.py
sklearn_evaluation/plot/matplotlib/bar.py
sklearn_evaluation/plot/matplotlib/data_grid.py
sklearn_evaluation/plot/matplotlib/heatmap.py
sklearn_evaluation/preprocessing/__init__.py
sklearn_evaluation/preprocessing/binarize.py
sklearn_evaluation/report/__init__.py
sklearn_evaluation/report/model_evaluator.py
sklearn_evaluation-0.12.2.dist-info/LICENSE
sklearn_evaluation-0.12.2.dist-info/METADATA
sklearn_evaluation-0.12.2.dist-info/WHEEL
sklearn_evaluation-0.12.2.dist-info/top_level.txt
sklearn_evaluation-0.12.2.dist-info/RECORD
