Metadata-Version: 2.1
Name: sklearn-evaluation
Version: 0.12.2
Summary: scikit-learn model evaluation made easy: plots, tables andmarkdown reports.
Home-page: http://github.com/ploomber/sklearn-evaluation
Download-URL: https://github.com/ploomber/sklearn-evaluation/tarball/0.12.2
Author: Ploomber
Author-email: contact@ploomber.io
License: Apache 2
Keywords: datascience,machinelearning
License-File: LICENSE
Requires-Dist: ploomber-core (>=0.2.6)
Requires-Dist: ploomber-extension
Requires-Dist: scikit-learn
Requires-Dist: matplotlib
Requires-Dist: decorator
Requires-Dist: tabulate
Requires-Dist: jinja2
Requires-Dist: mistune
Requires-Dist: pandas
Requires-Dist: nbformat
Requires-Dist: ipython
Requires-Dist: black
Requires-Dist: parso
Requires-Dist: importlib-metadata ; python_version < "3.8"
Provides-Extra: dev
Requires-Dist: pkgmt ; extra == 'dev'
Requires-Dist: jupytext ; extra == 'dev'
Requires-Dist: ploomber-engine ; extra == 'dev'
Requires-Dist: ipykernel ; extra == 'dev'
Requires-Dist: pytest (<8) ; extra == 'dev'
Requires-Dist: pytest-cov ; extra == 'dev'
Requires-Dist: coveralls (<3) ; extra == 'dev'
Requires-Dist: altair ; extra == 'dev'
Requires-Dist: lxml ; extra == 'dev'
Requires-Dist: matplotlib (<3.8) ; extra == 'dev'
